hamctrl/__init__.py
hamctrl/hamctrl.py
hamctrl-0.0.1.dist-info/LICENSE
hamctrl-0.0.1.dist-info/METADATA
hamctrl-0.0.1.dist-info/WHEEL
hamctrl-0.0.1.dist-info/top_level.txt
hamctrl-0.0.1.dist-info/RECORD
