Metadata-Version: 2.1
Name: hamctrl
Version: 0.0.1
Summary: Control-Library for Hamster
Author: Marcel Miljak
Author-email: mmiljak@tsn.at
License: UNKNOWN
Platform: UNKNOWN
Classifier: Programming Language :: Python :: 3
Classifier: License :: OSI Approved :: MIT License
Classifier: Operating System :: OS Independent
Requires-Python: >=3.6
License-File: LICENSE
